bond_pricing/__init__.py
bond_pricing/key_rates.py
bond_pricing/no_scipy_workarounds.py
bond_pricing/present_value.py
bond_pricing/simple_bonds.py
bond_pricing/utils.py
bond_pricing/zero_curve_bond_price.py
bond_pricing-0.7.3.dist-info/LICENSE
bond_pricing-0.7.3.dist-info/METADATA
bond_pricing-0.7.3.dist-info/WHEEL
bond_pricing-0.7.3.dist-info/top_level.txt
bond_pricing-0.7.3.dist-info/RECORD
