Metadata-Version: 2.1
Name: bond_pricing
Version: 0.7.3
Summary: Bond Price with YTM/zero-curve & NPV, IRR, annuities
Author-email: "Jayanth R. Varma" <jrvarma@gmail.com>
Maintainer-email: "Jayanth R. Varma" <jrvarma@gmail.com>
License: OSI Approved :: GNU General Public License v3 (GPLv3)
Project-URL: Homepage, https://github.com/jrvarma/bond_pricing
Keywords: Bond Pricing,NPV and IRR,Zero yield curve,Annuities and Perpetuities
Classifier: Development Status :: 3 - Alpha
Classifier: Environment :: Console
Classifier: Intended Audience :: End Users/Desktop
Classifier: Programming Language :: Python :: 3
Requires-Python: >=3.0
License-File: LICENSE
Requires-Dist: numpy
Requires-Dist: pandas
Requires-Dist: scipy
